fastapi_nextauth_jwt/__init__.py
fastapi_nextauth_jwt/cookies.py
fastapi_nextauth_jwt/csrf.py
fastapi_nextauth_jwt/exceptions.py
fastapi_nextauth_jwt/fastapi_nextauth_jwt.py
fastapi_nextauth_jwt/operations.py
fastapi_nextauth_jwt-2.1.1.dist-info/licenses/LICENSE
fastapi_nextauth_jwt-2.1.1.dist-info/WHEEL
fastapi_nextauth_jwt-2.1.1.dist-info/METADATA
fastapi_nextauth_jwt-2.1.1.dist-info/RECORD
