Metadata-Version: 2.4
Name: fastapi_nextauth_jwt
Version: 2.1.1
Summary: A fastapi dependency used to decode jwt tokens generated by nextauth,
Author: Tom Catshoek
Classifier: License :: OSI Approved :: MIT License
License-File: LICENSE
Requires-Dist: fastapi
Requires-Dist: cryptography
Requires-Dist: python-jose[cryptography] >=3.4
Requires-Dist: pytest >=2.7.3 ; extra == "test"
Requires-Dist: pytest-cov ; extra == "test"
Requires-Dist: httpx ; extra == "test"
Project-URL: Home, https://github.com/TCatshoek/fastapi-nextauth-jwt
Provides-Extra: test
